korsubset/__init__.py
korsubset/__main__.py
korsubset/subset_font.py
korsubset/unicode-range.txt
korsubset-0.1.2.dist-info/LICENSE
korsubset-0.1.2.dist-info/METADATA
korsubset-0.1.2.dist-info/WHEEL
korsubset-0.1.2.dist-info/entry_points.txt
korsubset-0.1.2.dist-info/top_level.txt
korsubset-0.1.2.dist-info/RECORD
